MANIFEST.in
README.md
setup.py
ship_it/__init__.py
ship_it/__init__.pyc
ship_it/cli.py
ship_it/cli.pyc
ship_it/manifest.py
ship_it/manifest.pyc
ship_it/scripts.py
ship_it/virtualenv.py
ship_it/virtualenv.pyc
ship_it.egg-info/PKG-INFO
ship_it.egg-info/SOURCES.txt
ship_it.egg-info/dependency_links.txt
ship_it.egg-info/entry_points.txt
ship_it.egg-info/requires.txt
ship_it.egg-info/top_level.txt
ship_it/__pycache__/__init__.cpython-36.pyc
ship_it/__pycache__/cli.cpython-36.pyc
ship_it/__pycache__/manifest.cpython-36.pyc
ship_it/__pycache__/virtualenv.cpython-36.pyc