Metadata-Version: 1.0
Name: ship-it
Version: 0.11.0
Summary: thin build wrapper around fpm that enforces some best practices for creating deb/rpm packages for python applications
Home-page: https://github.com/robdennis/ship_it
Author: Rob Dennis
Author-email: rdennis+ship_it@gmail.com
License: MIT
Platform: UNKNOWN
